{
  "404": "404",
  "About": "About",
  "Cancel": "Cancel",
  "Edit": "Edit",
  "Enter": "Enter",
  "Enter password": "Enter password",
  "Enter username": "Enter username",
  "Exit": "Exit",
  "Login error": "Login error",
  "Profile": "Profile",
  "Save": "Save",
  "Sign in form": "Sign in form",
  "about": "about",
  "decrement": "decrement",
  "increment": "increment",
  "language": "language",
  "login": "login",
  "mainPage": "mainPage",
  "pageError": "pageError",
  "profilePage": "profilePage",
  "profile_Age": "profile_Age",
  "profile_Avatar": "profile_Avatar",
  "profile_AvatarLink": "profile_AvatarLink",
  "profile_City": "profile_City",
  "profile_Country": "profile_Country",
  "profile_Currency": "profile_Currency",
  "profile_Lastname": "profile_Lastname",
  "profile_Name": "profile_Name",
  "profile_Username": "profile_Username",
  "profile_incorrect_age": "profile_incorrect_age",
  "profile_incorrect_country": "profile_incorrect_country",
  "profile_incorrect_user_data": "profile_incorrect_user_data",
  "profile_load_error": "profile_load_error",
  "profile_no_data": "profile_no_data",
  "profile_reload": "profile_reload",
  "profile_server_error": "profile_server_error",
  "reloadPage": "reloadPage",
  "throw-error": "throw-error",
  "toggle": "toggle"
}
